scientistshiny/__init__.py
scientistshiny/base.py
scientistshiny/ca.py
scientistshiny/famd.py
scientistshiny/function.py
scientistshiny/hcpc.py
scientistshiny/mca.py
scientistshiny/mfa.py
scientistshiny/mfact.py
scientistshiny/mfamix.py
scientistshiny/mfaqual.py
scientistshiny/pca.py
scientistshiny/www/style.css
scientistshiny-0.0.2.dist-info/LICENSE.txt
scientistshiny-0.0.2.dist-info/METADATA
scientistshiny-0.0.2.dist-info/WHEEL
scientistshiny-0.0.2.dist-info/top_level.txt
scientistshiny-0.0.2.dist-info/RECORD
