Metadata-Version: 2.1
Name: scientistshiny
Version: 0.0.2
Summary: Python library to easily improve multivariate Exploratory Data Analysis graphs
Author: Duverier DJIFACK ZEBAZE
Author-email: duverierdjifack@gmail.com
Classifier: Programming Language :: Python :: 3
Classifier: License :: OSI Approved :: MIT License
Classifier: Operating System :: OS Independent
Requires-Python: >=3.10
License-File: LICENSE.txt
Requires-Dist: shiny (>=0.9)
Requires-Dist: numpy (>=1.26.4)
Requires-Dist: matplotlib (>=3.8.4)
Requires-Dist: scikit-learn (>=1.2.2)
Requires-Dist: pandas (>=2.2.2)
Requires-Dist: numexpr (>=2.10.0)
Requires-Dist: plotnine (>=0.10.1)
Requires-Dist: scientisttools (>=0.1.6)
